insights_sandbox/__init__.py
insights_sandbox/adapter.py
insights_sandbox/client.py
insights_sandbox/consumer.py
insights_sandbox/controller.py
insights_sandbox/protocol.py
insights_sandbox/runner.py
insights_sandbox/tests/__init__.py
insights_sandbox/tests/test_controller.py
insights_sandbox/tests/test_runner_adapter_proxy.py
insights_sandbox/tests/test_states.py
insights_sandbox-0.1.0.dist-info/METADATA
insights_sandbox-0.1.0.dist-info/WHEEL
insights_sandbox-0.1.0.dist-info/top_level.txt
insights_sandbox-0.1.0.dist-info/RECORD
