Metadata-Version: 2.1
Name: insights-sandbox
Version: 0.1.0
Summary: bubblewrap sandbox for insights components.
Home-page: https://github.com/RedHatInsights/insights-sandbox
Author: Red Hat, Inc.
Author-email: insights@redhat.com
License: Apache 2.0
Platform: UNKNOWN
Classifier: Development Status :: 4 - Beta
Classifier: Intended Audience :: Developers
Classifier: Natural Language :: English
Classifier: License :: OSI Approved :: Apache Software License
Classifier: Programming Language :: Python
Classifier: Programming Language :: Python :: 3.6
Classifier: Programming Language :: Python :: 3.7
Classifier: Programming Language :: Python :: 3.8
Requires-Dist: dill (==0.3.2)
Requires-Dist: insights-core
Requires-Dist: pyzmq (==19.0.0)
Provides-Extra: develop
Requires-Dist: sphinx-rtd-theme (==0.5.0) ; extra == 'develop'
Requires-Dist: Sphinx (==3.1.2) ; extra == 'develop'
Requires-Dist: setuptools (==41.6.0) ; extra == 'develop'
Requires-Dist: IPython (==7.16.1) ; extra == 'develop'
Requires-Dist: wheel (==0.34.2) ; extra == 'develop'
Requires-Dist: pytest (==5.4.3) ; extra == 'develop'
Requires-Dist: black (==19.10b0) ; extra == 'develop'
Requires-Dist: flake8 (==3.8.3) ; extra == 'develop'
Provides-Extra: docs
Requires-Dist: sphinx-rtd-theme (==0.5.0) ; extra == 'docs'
Requires-Dist: Sphinx (==3.1.2) ; extra == 'docs'
